LICENSE.txt
README.md
setup.cfg
setup.py
xuanpolicy/__init__.py
xuanpolicy.egg-info/PKG-INFO
xuanpolicy.egg-info/SOURCES.txt
xuanpolicy.egg-info/dependency_links.txt
xuanpolicy.egg-info/requires.txt
xuanpolicy.egg-info/top_level.txt
xuanpolicy/common/__init__.py
xuanpolicy/common/common_tools.py
xuanpolicy/common/memory_tools.py
xuanpolicy/common/memory_tools_marl.py
xuanpolicy/common/segtree_tool.py
xuanpolicy/common/statistic_tools.py
xuanpolicy/configs/__init__.py
xuanpolicy/configs/basic.yaml
xuanpolicy/configs/a2c/atari.yaml
xuanpolicy/configs/a2c/mujoco.yaml
xuanpolicy/configs/a2c/box2d/BipedalWalker-v3.yaml
xuanpolicy/configs/a2c/box2d/LunarLander-v2.yaml
xuanpolicy/configs/a2c/classic_control/Acrobot-v1.yaml
xuanpolicy/configs/a2c/classic_control/CartPole-v1.yaml
xuanpolicy/configs/a2c/classic_control/MountainCar-v0.yaml
xuanpolicy/configs/a2c/classic_control/Pendulum-v1.yaml
xuanpolicy/configs/c51/atari.yaml
xuanpolicy/configs/c51/box2d/CarRacing-v2.yaml
xuanpolicy/configs/c51/box2d/LunarLander-v2.yaml
xuanpolicy/configs/c51/classic_control/Acrobot-v1.yaml
xuanpolicy/configs/c51/classic_control/CartPole-v1.yaml
xuanpolicy/configs/c51/classic_control/MountainCar-v0.yaml
xuanpolicy/configs/coma/mpe/simple_spread_v3.yaml
xuanpolicy/configs/coma/sc2/25m.yaml
xuanpolicy/configs/coma/sc2/2m_vs_1z.yaml
xuanpolicy/configs/coma/sc2/3m.yaml
xuanpolicy/configs/coma/sc2/5m_vs_6m.yaml
xuanpolicy/configs/coma/sc2/8m.yaml
xuanpolicy/configs/coma/sc2/8m_vs_9m.yaml
xuanpolicy/configs/coma/sc2/MMM2.yaml
xuanpolicy/configs/coma/sc2/corridor.yaml
xuanpolicy/configs/dcg/mpe/simple_spread_v3.yaml
xuanpolicy/configs/dcg/sc2/25m.yaml
xuanpolicy/configs/dcg/sc2/2m_vs_1z.yaml
xuanpolicy/configs/dcg/sc2/3m.yaml
xuanpolicy/configs/dcg/sc2/5m_vs_6m.yaml
xuanpolicy/configs/dcg/sc2/8m.yaml
xuanpolicy/configs/dcg/sc2/8m_vs_9m.yaml
xuanpolicy/configs/dcg/sc2/MMM2.yaml
xuanpolicy/configs/dcg/sc2/corridor.yaml
xuanpolicy/configs/ddpg/mujoco.yaml
xuanpolicy/configs/ddpg/box2d/BipedalWalker-v3.yaml
xuanpolicy/configs/ddpg/classic_control/Pendulum-v1.yaml
xuanpolicy/configs/ddqn/atari.yaml
xuanpolicy/configs/ddqn/box2d/CarRacing-v2.yaml
